targs.py
arguments/TargsArgumentParser.py
arguments/__init__.py
arguments/parse.py
tmux/__init__.py
tmux/window.py
tmux_xargs-0.0.8.dist-info/LICENSE
tmux_xargs-0.0.8.dist-info/METADATA
tmux_xargs-0.0.8.dist-info/WHEEL
tmux_xargs-0.0.8.dist-info/entry_points.txt
tmux_xargs-0.0.8.dist-info/top_level.txt
tmux_xargs-0.0.8.dist-info/RECORD
