Metadata-Version: 2.1
Name: tmux-xargs
Version: 0.0.8
Summary: targs: tmux + xargs
Home-page: https://github.com/ucchiee/targs
Download-URL: https://github.com/ucchiee/targs
Author: Yusuke Uchida
Author-email: fantomyuu0623@gmail.com
Maintainer: Yusuke Uchida
Maintainer-email: fantomyuu0623@gmail.com
License: MIT
Keywords: tmux xargs targs
License-File: LICENSE
